click_loguru/__init__.py
click_loguru-1.3.8.dist-info/LICENSE.txt
click_loguru-1.3.8.dist-info/LICENSE.artwork.txt
click_loguru-1.3.8.dist-info/WHEEL
click_loguru-1.3.8.dist-info/METADATA
click_loguru-1.3.8.dist-info/RECORD
