Metadata-Version: 2.1
Name: click-loguru
Version: 1.3.8
Summary: Logging to stderr and file for click applications.
Home-page: https://github.com/joelb123/click_loguru
License: BSD-3-Clause
Keywords: logging,click,console
Author: Joel Berendzen
Author-email: joel@generisbio.com
Requires-Python: >=3.7.1,<4.0
Classifier: Development Status :: 5 - Production/Stable
Classifier: Environment :: Console
Classifier: Intended Audience :: Developers
Classifier: License :: OSI Approved :: BSD License
Classifier: Natural Language :: English
Classifier: Operating System :: OS Independent
Classifier: Programming Language :: Python :: 3
Classifier: Programming Language :: Python :: 3.10
Classifier: Programming Language :: Python :: 3.7
Classifier: Programming Language :: Python :: 3.8
Classifier: Programming Language :: Python :: 3.9
Classifier: Topic :: Software Development :: User Interfaces
Requires-Dist: attrs (>=21.4.0)
Requires-Dist: click (>=8.0.1)
Requires-Dist: loguru (>=0.5.3)
Requires-Dist: memory_profiler (>=0.60.0)
Project-URL: Documentation, https://github.com/joelb123/click_loguru
